aswan/__init__.py
aswan/connection_session.py
aswan/constants.py
aswan/exceptions.py
aswan/metadata_handling.py
aswan/models.py
aswan/monitor_app.py
aswan/object_store.py
aswan/project.py
aswan/resources.py
aswan/security.py
aswan/simplified_functions.py
aswan/url_handler.py
aswan/utils.py
aswan/depot/__init__.py
aswan/depot/base.py
aswan/depot/remote.py
aswan/tests/__init__.py
aswan/tests/proxy_src.py
aswan/tests/godel_src/__init__.py
aswan/tests/godel_src/app.py
aswan/tests/godel_src/handlers.py
aswan/tests/godel_src/test_pages/Alonzo_Church.html
aswan/tests/godel_src/test_pages/Axiom.html
aswan/tests/godel_src/test_pages/Entscheidungsproblem
aswan/tests/godel_src/test_pages/Halting_problem.html
aswan/tests/godel_src/test_pages/godel_wiki.html
aswan/tests/godel_src/test_pages/jstest.html
aswan/tests/godel_src/test_pages/jstest_bad.html
aswan/tests/godel_src/test_pages/jstest_minus.html
aswan/tests/godel_src/test_pages/test_json.json
aswan/tests/integration/test_godel.py
aswan/tests/integration/test_godel_load.py
aswan/tests/unit/__init__.py
aswan/tests/unit/test_conn_session.py
aswan/tests/unit/test_depot.py
aswan/tests/unit/test_depot_remotes.py
aswan/tests/unit/test_metadata_handling.py
aswan/tests/unit/test_monitor_app.py
aswan/tests/unit/test_object_store.py
aswan/tests/unit/test_project_class.py
aswan/tests/unit/test_proxy.py
aswan/tests/unit/test_simplified_functions.py
aswan/tests/unit/test_utils.py
aswan/tests/unit/test_webext_session.py
aswan-0.5.15.dist-info/entry_points.txt
aswan-0.5.15.dist-info/LICENSE
aswan-0.5.15.dist-info/WHEEL
aswan-0.5.15.dist-info/METADATA
aswan-0.5.15.dist-info/RECORD
