Metadata-Version: 2.1
Name: aswan
Version: 0.5.15
Summary: Data collection manager
Author-email: Endre Márk Borza <endremborza@gmail.com>
Requires-Python: >=3.10
Requires-Dist: requests
Requires-Dist: beautifulsoup4
Requires-Dist: html5lib
Requires-Dist: selenium
Requires-Dist: sqlalchemy
Requires-Dist: pyyaml
Requires-Dist: typer
Requires-Dist: brotli
Requires-Dist: flask
Requires-Dist: flask-cors
Requires-Dist: atqo>=0.3.0
Requires-Dist: branthebuilder[doc] ; extra == "doc"
Requires-Dist: pandas ; extra == "monitor"
Requires-Dist: dash ; extra == "monitor"
Requires-Dist: dash-bootstrap-components ; extra == "monitor"
Requires-Dist: zimmauth[ssh,env] ; extra == "remote"
Requires-Dist: branthebuilder ; extra == "test"
Requires-Dist: zimmauth[test] ; extra == "test"
Project-URL: Homepage, https://github.com/endremborza/aswan
Provides-Extra: doc
Provides-Extra: monitor
Provides-Extra: remote
Provides-Extra: test
